Metadata-Version: 1.1
Name: scripty
Version: 0.1.4
Summary: Script runner to execute ELT and load tasks by Equinox
Home-page: UNKNOWN
Author: Equinox Fitness
Author-email: UNKNOWN
License: MIT
Platform: UNKNOWN
Classifier: Development Status :: 5 - Production/Stable
Classifier: Intended Audience :: Developers
Classifier: Natural Language :: English
Classifier: License :: OSI Approved :: MIT License
Classifier: Programming Language :: Python :: 3.6
